pqcryptography/PQAsymmetricCryptography.py
pqcryptography/SymmetricEncryption.py
pqcryptography/__init__.py
pqcryptography-0.0.3.dist-info/LICENSE
pqcryptography-0.0.3.dist-info/METADATA
pqcryptography-0.0.3.dist-info/WHEEL
pqcryptography-0.0.3.dist-info/top_level.txt
pqcryptography-0.0.3.dist-info/RECORD
