Metadata-Version: 2.1
Name: pqcryptography
Version: 0.0.3
Summary: easy post quantum cryptography library
Home-page: https://github.com/FunDan3/pqcryptography/
Author: Fun_Dan3
Author-email: dfr34560@gmail.com
Project-URL: Bug Tracker, https://github.com/FunDan3/pqcryptography/issues
Classifier: Programming Language :: Python :: 3
Classifier: License :: OSI Approved :: MIT License
Classifier: Operating System :: OS Independent
Requires-Python: >=3.8
License-File: LICENSE
Requires-Dist: pycryptodome
Requires-Dist: liboqs
